{
	"configurations" : 
	[
		{
			"abstractTargets" : 
			[
				{
					"directoryIndex" : 0,
					"id" : "CURL::ZLIB::@6890427a1f51a3e7e1df",
					"jsonFile" : "target-CURL__ZLIB-Debug-b551028a823f589051af.json",
					"name" : "CURL::ZLIB",
					"projectIndex" : 0
				},
				{
					"directoryIndex" : 0,
					"id" : "CURL::libcurl_shared::@6890427a1f51a3e7e1df",
					"jsonFile" : "target-CURL__libcurl_shared-Debug-e4aa247f430d3d3ebb30.json",
					"name" : "CURL::libcurl_shared",
					"projectIndex" : 0
				},
				{
					"directoryIndex" : 0,
					"id" : "CURL::win32_winsock::@6890427a1f51a3e7e1df",
					"jsonFile" : "target-CURL__win32_winsock-Debug-ca7b7d236a05d182b497.json",
					"name" : "CURL::win32_winsock",
					"projectIndex" : 0
				},
				{
					"directoryIndex" : 0,
					"id" : "ZLIB::ZLIB::@6890427a1f51a3e7e1df",
					"jsonFile" : "target-ZLIB__ZLIB-Debug-7fcef085cf1aff955191.json",
					"name" : "ZLIB::ZLIB",
					"projectIndex" : 0
				},
				{
					"directoryIndex" : 0,
					"id" : "cpr::cpr::@6890427a1f51a3e7e1df",
					"jsonFile" : "target-cpr__cpr-Debug-b16902843bf41783d419.json",
					"name" : "cpr::cpr",
					"projectIndex" : 0
				},
				{
					"directoryIndex" : 0,
					"id" : "nlohmann_json::@6890427a1f51a3e7e1df",
					"jsonFile" : "target-nlohmann_json-Debug-badae660517dc3c85b4d.json",
					"name" : "nlohmann_json",
					"projectIndex" : 0
				},
				{
					"directoryIndex" : 0,
					"id" : "nlohmann_json::nlohmann_json::@6890427a1f51a3e7e1df",
					"jsonFile" : "target-nlohmann_json__nlohmann_json-Debug-35e3034de4c11c2d0e20.json",
					"name" : "nlohmann_json::nlohmann_json",
					"projectIndex" : 0
				}
			],
			"directories" : 
			[
				{
					"abstractTargetIndexes" : 
					[
						0,
						1,
						2,
						3,
						4,
						5,
						6
					],
					"build" : ".",
					"jsonFile" : "directory-.-Debug-f6f22219c74102c3da70.json",
					"minimumCMakeVersion" : 
					{
						"string" : "3.10"
					},
					"projectIndex" : 0,
					"source" : ".",
					"targetIndexes" : 
					[
						0
					]
				}
			],
			"name" : "Debug",
			"projects" : 
			[
				{
					"abstractTargetIndexes" : 
					[
						0,
						1,
						2,
						3,
						4,
						5,
						6
					],
					"directoryIndexes" : 
					[
						0
					],
					"name" : "TlumaczPojec",
					"targetIndexes" : 
					[
						0
					]
				}
			],
			"targets" : 
			[
				{
					"directoryIndex" : 0,
					"id" : "TlumaczPojec::@6890427a1f51a3e7e1df",
					"jsonFile" : "target-TlumaczPojec-Debug-54d44cac3c094460f90a.json",
					"name" : "TlumaczPojec",
					"projectIndex" : 0
				}
			]
		}
	],
	"kind" : "codemodel",
	"paths" : 
	{
		"build" : "C:/Users/Julia/Desktop/projekt-aplikacja-tlumaczaca-material/build",
		"source" : "C:/Users/Julia/Desktop/projekt-aplikacja-tlumaczaca-material"
	},
	"version" : 
	{
		"major" : 2,
		"minor" : 9
	}
}
